cleancredits/__init__.py
cleancredits/__version__.py
cleancredits/cli.py
cleancredits/cli_test.py
cleancredits/gui.py
cleancredits/helpers.py
cleancredits/helpers_test.py
cleancredits/param_types.py
cleancredits/param_types_test.py
cleancredits-2.0.0.dist-info/LICENSE
cleancredits-2.0.0.dist-info/METADATA
cleancredits-2.0.0.dist-info/WHEEL
cleancredits-2.0.0.dist-info/entry_points.txt
cleancredits-2.0.0.dist-info/top_level.txt
cleancredits-2.0.0.dist-info/RECORD
