Metadata-Version: 2.1
Name: cleancredits
Version: 2.0.0
Summary: A very simple tool for removing on-screen text from video, using a user-provided mask
Home-page: https://github.com/BeatriceEagle/cleancredits
Author: BeatriceEagle
Author-email: beatriceeagle@gmail.com
License: GPL version 3
Classifier: License :: OSI Approved :: MIT License
Classifier: Programming Language :: Python
Classifier: Programming Language :: Python :: 3
Classifier: Programming Language :: Python :: 3.6
Classifier: Topic :: Multimedia :: Video
Requires-Python: >=3.6.0
License-File: LICENSE
Requires-Dist: click (<9.0,>=8.1)
Requires-Dist: ffmpeg-python (<1.0,>=0.2)
Requires-Dist: opencv-python
Requires-Dist: Pillow
